Metadata-Version: 2.1
Name: odoo-addon-shift
Version: 16.0.1.1.1.3
Requires-Python: >=3.10
Requires-Dist: odoo>=16.0a,<16.1dev
Summary: Generate and manage shifts for cooperators.
Home-page: https://github.com/beescoop/Obeesdoo
License: AGPL-3
Author: Thibault Francois, Elouan Le Bars, Coop IT Easy SC, Odoo Community Association (OCA),
Author-email: support@odoo-community.org
Classifier: Programming Language :: Python
Classifier: Framework :: Odoo
Classifier: Framework :: Odoo :: 16.0
Classifier: License :: OSI Approved :: GNU Affero General Public License v3
